mdmi/__init__.py
mdmi/cli.py
mdmi/fake_midi_interface.py
mdmi/fm_operator.py
mdmi/midi_interface.py
mdmi/mido_midi_interface.py
mdmi/preset.py
mdmi/preset_parsers.py
mdmi/sysex_generator.py
mdmi/ui.py
mdmi/util.py
mdmi/commands/__init__.py
mdmi/commands/clear_all_presets.py
mdmi/commands/clear_preset.py
mdmi/commands/common.py
mdmi/commands/dump_channel.py
mdmi/commands/dump_common.py
mdmi/commands/dump_preset.py
mdmi/commands/list_ports.py
mdmi/commands/list_wopn.py
mdmi/commands/load_preset.py
mdmi/commands/perf_test.py
mdmi/commands/ping.py
mdmi/presets/dmp.py
mdmi/presets/dmp_parser.py
mdmi/presets/tfi.py
mdmi/presets/tfi_parser.py
mdmi/presets/wopn.py
mdmi/presets/wopn_bank.py
mdmi/presets/wopn_instrument.py
mdmi/presets/wopn_parser.py
mdmi_cli-0.8.0.dist-info/licenses/LICENSE
mdmi_cli-0.8.0.dist-info/METADATA
mdmi_cli-0.8.0.dist-info/WHEEL
mdmi_cli-0.8.0.dist-info/entry_points.txt
mdmi_cli-0.8.0.dist-info/top_level.txt
mdmi_cli-0.8.0.dist-info/RECORD
