Metadata-Version: 2.4
Name: mdmi-cli
Version: 0.8.0
Summary: CLI tool for working with the Mega Drive MIDI Interface (MDMI)
Author: rhargreaves
License: MIT
Project-URL: Homepage, https://github.com/rhargreaves/mdmi-cli
Project-URL: Repository, https://github.com/rhargreaves/mdmi-cli
Project-URL: Issues, https://github.com/rhargreaves/mdmi-cli/issues
Keywords: midi,sysex,mega-drive,fm-synthesis,cli
Classifier: Development Status :: 4 - Beta
Classifier: Intended Audience :: Developers
Classifier: License :: OSI Approved :: MIT License
Classifier: Operating System :: OS Independent
Classifier: Programming Language :: Python :: 3
Classifier: Programming Language :: Python :: 3.10
Classifier: Programming Language :: Python :: 3.11
Classifier: Programming Language :: Python :: 3.12
Classifier: Topic :: Multimedia :: Sound/Audio :: MIDI
Classifier: Topic :: Software Development :: Libraries :: Python Modules
Requires-Python: >=3.10
License-File: LICENSE
Requires-Dist: click>=8.0.0
Requires-Dist: mido>=1.2.10
Requires-Dist: python-rtmidi>=1.5.8
Requires-Dist: bitstruct>=8.15.0
Requires-Dist: matplotlib>=3.5.0
Requires-Dist: numpy>=1.21.0
Provides-Extra: dev
Requires-Dist: pytest>=7.0.0; extra == "dev"
Requires-Dist: pytest-mock>=3.10.0; extra == "dev"
Requires-Dist: ruff>=0.1.0; extra == "dev"
Dynamic: license-file
